gpt_assistant/__init__.py
gpt_assistant/gpt_assistant.py
gpt_assistant-1.1.dist-info/METADATA
gpt_assistant-1.1.dist-info/WHEEL
gpt_assistant-1.1.dist-info/top_level.txt
gpt_assistant-1.1.dist-info/RECORD
