Metadata-Version: 2.1
Name: gpt-assistant
Version: 1.1
Summary: Speech-based GPT using Python
Home-page: https://github.com/2vin/gpt-assistant
Author: Vinay
Author-email: vinay@connect.vin
License: UNKNOWN
Platform: UNKNOWN
